neuropull/__init__.py
neuropull/graph/README.md
neuropull/graph/__init__.py
neuropull/graph/adjacency.py
neuropull/graph/base_frame.py
neuropull/graph/matrix.py
neuropull/graph/matrix_frame.py
neuropull/graph/network_frame.py
neuropull/graph/types.py
neuropull/load/__init__.py
neuropull/load/load.py
neuropull/neuropull.py
neuropull-0.2.0.dist-info/WHEEL
neuropull-0.2.0.dist-info/LICENSE
neuropull-0.2.0.dist-info/METADATA
neuropull-0.2.0.dist-info/RECORD
